<?xml version="1.0" encoding="UTF-8"?>
<manifest xmlns="http://www.overheid.nl/2017/lvbb">
    <bestand>
        <bestandsnaam>akn_nl_bill_gm0297-3520-01.xml</bestandsnaam>
        <contentType>application/xml</contentType>
    </bestand>
    <bestand>
        <bestandsnaam>manifest.xml</bestandsnaam>
        <contentType>application/xml</contentType>
    </bestand>
    <bestand>
        <bestandsnaam>opdracht.xml</bestandsnaam>
        <contentType>application/xml</contentType>
    </bestand>
    <!-- FOUT: LVBB1009 Zijn alle bestanden genoemd in manifest aanwezig in zip? -->
    <bestand>
        <bestandsnaam>bestaat_niet.xml</bestandsnaam>
        <contentType>application/xml</contentType>
    </bestand>
    <bestand>
        <bestandsnaam>GIO001-Bedrijf_categorie_2.xml</bestandsnaam>
        <contentType>application/xml</contentType>
    </bestand>
    <bestand>
        <bestandsnaam>GIO002-Centrumgebied.xml</bestandsnaam>
        <contentType>application/xml</contentType>
    </bestand>
    <bestand>
        <bestandsnaam>GIO003-Zone_A.xml</bestandsnaam>
        <contentType>application/xml</contentType>
    </bestand>
    <bestand>
        <bestandsnaam>GIO004-Zone_B.xml</bestandsnaam>
        <contentType>application/xml</contentType>
    </bestand>
    <bestand>
        <bestandsnaam>GIO005-Speelhal.xml</bestandsnaam>
        <contentType>application/xml</contentType>
    </bestand>
    <bestand>
        <bestandsnaam>GIO006-Bouwhoogte.xml</bestandsnaam>
        <contentType>application/xml</contentType>
    </bestand>
    <bestand>
        <bestandsnaam>GIO007-Welstand.xml</bestandsnaam>
        <contentType>application/xml</contentType>
    </bestand>
    <bestand>
        <bestandsnaam>GIO008-Zuilichem.xml</bestandsnaam>
        <contentType>application/xml</contentType>
    </bestand>
    <bestand>
        <bestandsnaam>GIO009-Zaltbommel.xml</bestandsnaam>
        <contentType>application/xml</contentType>
    </bestand>
    <bestand>
        <bestandsnaam>Bedrijf_categorie_2.gml</bestandsnaam>
        <contentType>application/gml+xml</contentType>
    </bestand>
    <bestand>
        <bestandsnaam>Bouwhoogte.gml</bestandsnaam>
        <contentType>application/gml+xml</contentType>
    </bestand>
    <bestand>
        <bestandsnaam>Centrumgebied.gml</bestandsnaam>
        <contentType>application/gml+xml</contentType>
    </bestand>
    <bestand>
        <bestandsnaam>Speelhal.gml</bestandsnaam>
        <contentType>application/gml+xml</contentType>
    </bestand>
    <bestand>
        <bestandsnaam>Welstand.gml</bestandsnaam>
        <contentType>application/gml+xml</contentType>
    </bestand>
    <bestand>
        <bestandsnaam>Zaltbommel.gml</bestandsnaam>
        <contentType>application/gml+xml</contentType>
    </bestand>
    <bestand>
        <bestandsnaam>Zone_A.gml</bestandsnaam>
        <contentType>application/gml+xml</contentType>
    </bestand>
    <bestand>
        <bestandsnaam>Zone_B.gml</bestandsnaam>
        <contentType>application/gml+xml</contentType>
    </bestand>
    <bestand>
        <bestandsnaam>Zuilichem.gml</bestandsnaam>
        <contentType>application/gml+xml</contentType>
    </bestand>
    <!-- FOUT: 
        GEO0001	losgekoppeld middendeel 
        GEO0002	dubbele identieke ringen 
        GEO0003	gat ligt buiten de buitenrand 
        GEO0004	ongeldige coordinaat 
        GEO0005	gaten in een gat 
        GEO0006	buitenrand binnen een buitenrand 
        GEO0007	niet gesloten ring 
        GEO0008	ring doorsnijdt zichzelf 
        GEO0009	zichzelf doorsnijdende structuur 
        GEO0010	geometrische component heeft te weinig punten 
        GEO0011	coordinaat komt meerdere keren voor 
        GEO0012	coordinaat systeem niet ondersteund 
        GEOMETRY.03.5	geometrie niet conform crs configuratie 
    -->
    <bestand>
        <bestandsnaam>FouteGebieden.gml</bestandsnaam>
        <contentType>application/gml+xml</contentType>
    </bestand>
    <!-- FOUT: LVBB3009	Valideert het gml document tegen het schema -->
    <bestand>
        <bestandsnaam>GMLValideertNietSchema.gml</bestandsnaam>
        <contentType>application/gml+xml</contentType>
    </bestand>
    <bestand>
        <bestandsnaam>NietInBesluit.gml</bestandsnaam>
        <contentType>application/gml+xml</contentType>
    </bestand>
    <!-- FOUT: LVBB3505	De aangeleverde IO voor validatie komt niet voor in het besluit -->
    <!-- FOUT: LVBB3509	Alle aanleverde io(s) moeten voorkomen in het besluit -->
    <bestand>
        <bestandsnaam>NietInBesluit.xml</bestandsnaam>
        <contentType>application/xml</contentType>
    </bestand>
    <!-- FOUT: LVBB3507	Het content-type van de het meegeleverd bestand bij de IO is 'application/pdf' of 'application/gml+xml'  -->
    <bestand>
        <bestandsnaam>GMLNietGevonden.xml</bestandsnaam>
        <contentType>application/xml</contentType>
    </bestand>
    <bestand>
        <bestandsnaam>manifest-ow.xml</bestandsnaam>
        <contentType>application/xml</contentType>
    </bestand>
    <bestand>
        <bestandsnaam>owActiviteiten-Gemeentestad.xml</bestandsnaam>
        <contentType>application/xml</contentType>
    </bestand>
    <bestand>
        <bestandsnaam>owGebiedsaanwijzingen-Gemeentestad.xml</bestandsnaam>
        <contentType>application/xml</contentType>
    </bestand>
    <bestand>
        <bestandsnaam>owKaart.xml</bestandsnaam>
        <contentType>application/xml</contentType>
    </bestand>
    <bestand>
        <bestandsnaam>owLocaties-Gemeentestad.xml</bestandsnaam>
        <contentType>application/xml</contentType>
    </bestand>
    <bestand>
        <bestandsnaam>owOmgevingsnormOmgevingswaarde.xml</bestandsnaam>
        <contentType>application/xml</contentType>
    </bestand>
    <bestand>
        <bestandsnaam>owPons-Gemeentestad.xml</bestandsnaam>
        <contentType>application/xml</contentType>
    </bestand>
    <bestand>
        <bestandsnaam>owRegeltekst-Gemeentestad.xml</bestandsnaam>
        <contentType>application/xml</contentType>
    </bestand>
    <bestand>
        <bestandsnaam>owRegelingsgebied.xml</bestandsnaam>
        <contentType>application/xml</contentType>
    </bestand>
    <!-- FOUT: LVBB1013	Plaatjes mogen geen transparantie hebben -->
    <bestand>
        <bestandsnaam>transparent_cloud.png</bestandsnaam>
        <contentType>image/png</contentType>
    </bestand>
    <bestand>
        <bestandsnaam>dont_look_in_browser.gif</bestandsnaam>
        <contentType>image/gif</contentType>
    </bestand>
    <!-- FOUT: LVBB1018	Komt het gespecificeerde contenttype van een afbeelding overeen met het werkelijke contenttype? -->
    <!-- FOUT: LVBB1021	Komt het gespecificeerde contenttype overeen met het werkelijke contenttype? -->
    <bestand>
        <bestandsnaam>dont_look_in_browser_2.gif</bestandsnaam>
        <contentType>image/png</contentType>
    </bestand>
    <!-- FOUT: LVBB1017	Is het bestandsformaat van de afbeelding een formaat dat ondersteund wordt? -->
    <!-- FOUT: LVBB1019	Komt het gespecificeerde contenttype voor in de lijst met toegestane mimetypes? -->
    <bestand>
        <bestandsnaam>dont_look_in_browser_3.gif</bestandsnaam>
        <contentType>image/bmp</contentType>
    </bestand>
    <!-- FOUT: LVBB1020	Is het aangeleverde contenttype ingevuld? -->
    <bestand>
        <bestandsnaam>dont_look_in_browser_4.xxx</bestandsnaam>
    </bestand>
</manifest>